mason/__init__.py
mason/callbacks.py
mason/cli.py
mason/events.py
mason/exceptions.py
mason/http/__init__.py
mason/http/aiohttp.py
mason/http/sanic.py
mason/io.py
mason/library.py
mason/middleware.py
mason/node.py
mason/nodes/__init__.py
mason/nodes/blueprint.py
mason/nodes/flow.py
mason/nodes/logic.py
mason/nodes/math.py
mason/port.py
mason/proto/__init__.py
mason/proto/blueprint.proto
mason/proto/blueprint_pb2.py
mason/proto/config.proto
mason/proto/config_pb2.py
mason/proto/library.proto
mason/proto/library_pb2.py
mason/schema.py
mason/storage.py
mason/storages/__init__.py
mason/storages/filesystem.py
mason/utils.py
mason_framework-0.0.10.dist-info/entry_points.txt
mason_framework-0.0.10.dist-info/WHEEL
mason_framework-0.0.10.dist-info/METADATA
mason_framework-0.0.10.dist-info/RECORD
